{
  "generated_at": "2026-01-29T03:24:28.824Z",
  "results": [
    {
      "name": "Artificial intelligence",
      "url": "https://en.wikipedia.org/wiki/Artificial_intelligence",
      "observed_at": "2026-01-29T03:24:19.707Z",
      "http_status": 200,
      "response_time_ms": 161,
      "content_length": 226160,
      "etag": null,
      "title_hash": "e47f2cf7047cfdba8d6e50a8c83d3d49bd967ec099a48462d347833531bf4f84",
      "health_score": 1,
      "volatility": "stable",
      "change_count_12m": 0,
      "last_change_detected": null,
      "citation_risk": "low",
      "recommended_action": "safe_to_cite",
      "signals": []
    },
    {
      "name": "History of artificial intelligence",
      "url": "https://en.wikipedia.org/wiki/History_of_artificial_intelligence",
      "observed_at": "2026-01-29T03:24:19.766Z",
      "http_status": 200,
      "response_time_ms": 58,
      "content_length": 138817,
      "etag": null,
      "title_hash": "e47f2cf7047cfdba8d6e50a8c83d3d49bd967ec099a48462d347833531bf4f84",
      "health_score": 1,
      "volatility": "stable",
      "change_count_12m": 0,
      "last_change_detected": null,
      "citation_risk": "low",
      "recommended_action": "safe_to_cite",
      "signals": []
    },
    {
      "name": "Philosophy of artificial intelligence",
      "url": "https://en.wikipedia.org/wiki/Philosophy_of_artificial_intelligence",
      "observed_at": "2026-01-29T03:24:19.825Z",
      "http_status": 200,
      "response_time_ms": 59,
      "content_length": 66423,
      "etag": null,
      "title_hash": "e47f2cf7047cfdba8d6e50a8c83d3d49bd967ec099a48462d347833531bf4f84",
      "health_score": 1,
      "volatility": "moderate",
      "change_count_12m": 3,
      "last_change_detected": "2026-01-27",
      "citation_risk": "low",
      "recommended_action": "safe_to_cite",
      "signals": []
    },
    {
      "name": "AI alignment",
      "url": "https://en.wikipedia.org/wiki/AI_alignment",
      "observed_at": "2026-01-29T03:24:20.143Z",
      "http_status": 200,
      "response_time_ms": 318,
      "content_length": 0,
      "etag": null,
      "title_hash": "e47f2cf7047cfdba8d6e50a8c83d3d49bd967ec099a48462d347833531bf4f84",
      "health_score": 0.8,
      "volatility": "moderate",
      "change_count_12m": 4,
      "last_change_detected": "2026-01-29",
      "citation_risk": "low",
      "recommended_action": "safe_to_cite",
      "signals": [
        "content_shift"
      ]
    },
    {
      "name": "Artificial general intelligence",
      "url": "https://en.wikipedia.org/wiki/Artificial_general_intelligence",
      "observed_at": "2026-01-29T03:24:20.534Z",
      "http_status": 200,
      "response_time_ms": 391,
      "content_length": 0,
      "etag": null,
      "title_hash": "e47f2cf7047cfdba8d6e50a8c83d3d49bd967ec099a48462d347833531bf4f84",
      "health_score": 0.8,
      "volatility": "stable",
      "change_count_12m": 2,
      "last_change_detected": "2026-01-29",
      "citation_risk": "low",
      "recommended_action": "safe_to_cite",
      "signals": [
        "content_shift"
      ]
    },
    {
      "name": "Machine learning",
      "url": "https://en.wikipedia.org/wiki/Machine_learning",
      "observed_at": "2026-01-29T03:24:20.592Z",
      "http_status": 200,
      "response_time_ms": 58,
      "content_length": 131103,
      "etag": null,
      "title_hash": "e47f2cf7047cfdba8d6e50a8c83d3d49bd967ec099a48462d347833531bf4f84",
      "health_score": 1,
      "volatility": "stable",
      "change_count_12m": 2,
      "last_change_detected": "2026-01-23",
      "citation_risk": "low",
      "recommended_action": "safe_to_cite",
      "signals": []
    },
    {
      "name": "Supervised learning",
      "url": "https://en.wikipedia.org/wiki/Supervised_learning",
      "observed_at": "2026-01-29T03:24:20.648Z",
      "http_status": 200,
      "response_time_ms": 56,
      "content_length": 35103,
      "etag": null,
      "title_hash": "e47f2cf7047cfdba8d6e50a8c83d3d49bd967ec099a48462d347833531bf4f84",
      "health_score": 1,
      "volatility": "stable",
      "change_count_12m": 2,
      "last_change_detected": "2026-01-27",
      "citation_risk": "low",
      "recommended_action": "safe_to_cite",
      "signals": []
    },
    {
      "name": "Unsupervised learning",
      "url": "https://en.wikipedia.org/wiki/Unsupervised_learning",
      "observed_at": "2026-01-29T03:24:20.705Z",
      "http_status": 200,
      "response_time_ms": 57,
      "content_length": 42225,
      "etag": null,
      "title_hash": "e47f2cf7047cfdba8d6e50a8c83d3d49bd967ec099a48462d347833531bf4f84",
      "health_score": 1,
      "volatility": "stable",
      "change_count_12m": 2,
      "last_change_detected": "2026-01-26",
      "citation_risk": "low",
      "recommended_action": "safe_to_cite",
      "signals": []
    },
    {
      "name": "Reinforcement learning",
      "url": "https://en.wikipedia.org/wiki/Reinforcement_learning",
      "observed_at": "2026-01-29T03:24:20.729Z",
      "http_status": 200,
      "response_time_ms": 24,
      "content_length": 85789,
      "etag": null,
      "title_hash": "e47f2cf7047cfdba8d6e50a8c83d3d49bd967ec099a48462d347833531bf4f84",
      "health_score": 1,
      "volatility": "stable",
      "change_count_12m": 1,
      "last_change_detected": "2026-01-26",
      "citation_risk": "low",
      "recommended_action": "safe_to_cite",
      "signals": []
    },
    {
      "name": "Deep learning",
      "url": "https://en.wikipedia.org/wiki/Deep_learning",
      "observed_at": "2026-01-29T03:24:20.786Z",
      "http_status": 200,
      "response_time_ms": 57,
      "content_length": 148714,
      "etag": null,
      "title_hash": "e47f2cf7047cfdba8d6e50a8c83d3d49bd967ec099a48462d347833531bf4f84",
      "health_score": 1,
      "volatility": "stable",
      "change_count_12m": 1,
      "last_change_detected": "2026-01-26",
      "citation_risk": "low",
      "recommended_action": "safe_to_cite",
      "signals": []
    },
    {
      "name": "Neural network",
      "url": "https://en.wikipedia.org/wiki/Neural_network",
      "observed_at": "2026-01-29T03:24:20.807Z",
      "http_status": 200,
      "response_time_ms": 21,
      "content_length": 20724,
      "etag": null,
      "title_hash": "e47f2cf7047cfdba8d6e50a8c83d3d49bd967ec099a48462d347833531bf4f84",
      "health_score": 1,
      "volatility": "stable",
      "change_count_12m": 2,
      "last_change_detected": "2026-01-24",
      "citation_risk": "low",
      "recommended_action": "safe_to_cite",
      "signals": []
    },
    {
      "name": "Artificial neural network",
      "url": "https://en.wikipedia.org/wiki/Artificial_neural_network",
      "observed_at": "2026-01-29T03:24:20.863Z",
      "http_status": 200,
      "response_time_ms": 56,
      "content_length": 157299,
      "etag": null,
      "title_hash": "e47f2cf7047cfdba8d6e50a8c83d3d49bd967ec099a48462d347833531bf4f84",
      "health_score": 1,
      "volatility": "stable",
      "change_count_12m": 1,
      "last_change_detected": "2026-01-25",
      "citation_risk": "low",
      "recommended_action": "safe_to_cite",
      "signals": []
    },
    {
      "name": "Convolutional neural network",
      "url": "https://en.wikipedia.org/wiki/Convolutional_neural_network",
      "observed_at": "2026-01-29T03:24:20.884Z",
      "http_status": 200,
      "response_time_ms": 21,
      "content_length": 118719,
      "etag": null,
      "title_hash": "e47f2cf7047cfdba8d6e50a8c83d3d49bd967ec099a48462d347833531bf4f84",
      "health_score": 1,
      "volatility": "stable",
      "change_count_12m": 1,
      "last_change_detected": "2026-01-26",
      "citation_risk": "low",
      "recommended_action": "safe_to_cite",
      "signals": []
    },
    {
      "name": "Recurrent neural network",
      "url": "https://en.wikipedia.org/wiki/Recurrent_neural_network",
      "observed_at": "2026-01-29T03:24:21.012Z",
      "http_status": 200,
      "response_time_ms": 128,
      "content_length": 94786,
      "etag": null,
      "title_hash": "e47f2cf7047cfdba8d6e50a8c83d3d49bd967ec099a48462d347833531bf4f84",
      "health_score": 1,
      "volatility": "stable",
      "change_count_12m": 1,
      "last_change_detected": "2026-01-26",
      "citation_risk": "low",
      "recommended_action": "safe_to_cite",
      "signals": []
    },
    {
      "name": "Transformer (machine learning model)",
      "url": "https://en.wikipedia.org/wiki/Transformer_(machine_learning_model)",
      "observed_at": "2026-01-29T03:24:23.510Z",
      "http_status": 200,
      "response_time_ms": 2498,
      "content_length": 0,
      "etag": null,
      "title_hash": "e47f2cf7047cfdba8d6e50a8c83d3d49bd967ec099a48462d347833531bf4f84",
      "health_score": 0.8,
      "volatility": "moderate",
      "change_count_12m": 3,
      "last_change_detected": "2026-01-29",
      "citation_risk": "low",
      "recommended_action": "safe_to_cite",
      "signals": [
        "content_shift"
      ]
    },
    {
      "name": "Linear regression",
      "url": "https://en.wikipedia.org/wiki/Linear_regression",
      "observed_at": "2026-01-29T03:24:23.568Z",
      "http_status": 200,
      "response_time_ms": 58,
      "content_length": 81467,
      "etag": null,
      "title_hash": "e47f2cf7047cfdba8d6e50a8c83d3d49bd967ec099a48462d347833531bf4f84",
      "health_score": 1,
      "volatility": "stable",
      "change_count_12m": 2,
      "last_change_detected": "2026-01-28",
      "citation_risk": "low",
      "recommended_action": "safe_to_cite",
      "signals": []
    },
    {
      "name": "Logistic regression",
      "url": "https://en.wikipedia.org/wiki/Logistic_regression",
      "observed_at": "2026-01-29T03:24:23.625Z",
      "http_status": 200,
      "response_time_ms": 57,
      "content_length": 128166,
      "etag": null,
      "title_hash": "e47f2cf7047cfdba8d6e50a8c83d3d49bd967ec099a48462d347833531bf4f84",
      "health_score": 1,
      "volatility": "stable",
      "change_count_12m": 0,
      "last_change_detected": null,
      "citation_risk": "low",
      "recommended_action": "safe_to_cite",
      "signals": []
    },
    {
      "name": "Gradient descent",
      "url": "https://en.wikipedia.org/wiki/Gradient_descent",
      "observed_at": "2026-01-29T03:24:23.682Z",
      "http_status": 200,
      "response_time_ms": 57,
      "content_length": 64737,
      "etag": null,
      "title_hash": "e47f2cf7047cfdba8d6e50a8c83d3d49bd967ec099a48462d347833531bf4f84",
      "health_score": 1,
      "volatility": "stable",
      "change_count_12m": 2,
      "last_change_detected": "2026-01-28",
      "citation_risk": "low",
      "recommended_action": "safe_to_cite",
      "signals": []
    },
    {
      "name": "Backpropagation",
      "url": "https://en.wikipedia.org/wiki/Backpropagation",
      "observed_at": "2026-01-29T03:24:23.738Z",
      "http_status": 200,
      "response_time_ms": 56,
      "content_length": 75704,
      "etag": null,
      "title_hash": "e47f2cf7047cfdba8d6e50a8c83d3d49bd967ec099a48462d347833531bf4f84",
      "health_score": 1,
      "volatility": "stable",
      "change_count_12m": 2,
      "last_change_detected": "2026-01-26",
      "citation_risk": "low",
      "recommended_action": "safe_to_cite",
      "signals": []
    },
    {
      "name": "Loss function",
      "url": "https://en.wikipedia.org/wiki/Loss_function",
      "observed_at": "2026-01-29T03:24:23.794Z",
      "http_status": 200,
      "response_time_ms": 56,
      "content_length": 41193,
      "etag": null,
      "title_hash": "e47f2cf7047cfdba8d6e50a8c83d3d49bd967ec099a48462d347833531bf4f84",
      "health_score": 1,
      "volatility": "stable",
      "change_count_12m": 2,
      "last_change_detected": "2026-01-25",
      "citation_risk": "low",
      "recommended_action": "safe_to_cite",
      "signals": []
    },
    {
      "name": "Natural language processing",
      "url": "https://en.wikipedia.org/wiki/Natural_language_processing",
      "observed_at": "2026-01-29T03:24:23.850Z",
      "http_status": 200,
      "response_time_ms": 56,
      "content_length": 66372,
      "etag": null,
      "title_hash": "e47f2cf7047cfdba8d6e50a8c83d3d49bd967ec099a48462d347833531bf4f84",
      "health_score": 1,
      "volatility": "stable",
      "change_count_12m": 0,
      "last_change_detected": null,
      "citation_risk": "low",
      "recommended_action": "safe_to_cite",
      "signals": []
    },
    {
      "name": "Computer vision",
      "url": "https://en.wikipedia.org/wiki/Computer_vision",
      "observed_at": "2026-01-29T03:24:23.872Z",
      "http_status": 200,
      "response_time_ms": 22,
      "content_length": 67535,
      "etag": null,
      "title_hash": "e47f2cf7047cfdba8d6e50a8c83d3d49bd967ec099a48462d347833531bf4f84",
      "health_score": 1,
      "volatility": "moderate",
      "change_count_12m": 3,
      "last_change_detected": "2026-01-27",
      "citation_risk": "low",
      "recommended_action": "safe_to_cite",
      "signals": []
    },
    {
      "name": "Speech recognition",
      "url": "https://en.wikipedia.org/wiki/Speech_recognition",
      "observed_at": "2026-01-29T03:24:23.927Z",
      "http_status": 200,
      "response_time_ms": 55,
      "content_length": 96851,
      "etag": null,
      "title_hash": "e47f2cf7047cfdba8d6e50a8c83d3d49bd967ec099a48462d347833531bf4f84",
      "health_score": 1,
      "volatility": "stable",
      "change_count_12m": 1,
      "last_change_detected": "2026-01-24",
      "citation_risk": "low",
      "recommended_action": "safe_to_cite",
      "signals": []
    },
    {
      "name": "Knowledge representation",
      "url": "https://en.wikipedia.org/wiki/Knowledge_representation",
      "observed_at": "2026-01-29T03:24:24.169Z",
      "http_status": 200,
      "response_time_ms": 242,
      "content_length": 0,
      "etag": null,
      "title_hash": "e47f2cf7047cfdba8d6e50a8c83d3d49bd967ec099a48462d347833531bf4f84",
      "health_score": 1,
      "volatility": "moderate",
      "change_count_12m": 4,
      "last_change_detected": "2026-01-28",
      "citation_risk": "low",
      "recommended_action": "safe_to_cite",
      "signals": []
    },
    {
      "name": "Expert system",
      "url": "https://en.wikipedia.org/wiki/Expert_system",
      "observed_at": "2026-01-29T03:24:25.512Z",
      "http_status": 200,
      "response_time_ms": 1343,
      "content_length": 0,
      "etag": null,
      "title_hash": "e47f2cf7047cfdba8d6e50a8c83d3d49bd967ec099a48462d347833531bf4f84",
      "health_score": 0.8,
      "volatility": "moderate",
      "change_count_12m": 5,
      "last_change_detected": "2026-01-29",
      "citation_risk": "low",
      "recommended_action": "safe_to_cite",
      "signals": [
        "content_shift"
      ]
    },
    {
      "name": "Feature engineering",
      "url": "https://en.wikipedia.org/wiki/Feature_engineering",
      "observed_at": "2026-01-29T03:24:25.605Z",
      "http_status": 200,
      "response_time_ms": 93,
      "content_length": 34938,
      "etag": null,
      "title_hash": "e47f2cf7047cfdba8d6e50a8c83d3d49bd967ec099a48462d347833531bf4f84",
      "health_score": 1,
      "volatility": "stable",
      "change_count_12m": 2,
      "last_change_detected": "2026-01-24",
      "citation_risk": "low",
      "recommended_action": "safe_to_cite",
      "signals": []
    },
    {
      "name": "Overfitting",
      "url": "https://en.wikipedia.org/wiki/Overfitting",
      "observed_at": "2026-01-29T03:24:25.662Z",
      "http_status": 200,
      "response_time_ms": 57,
      "content_length": 42196,
      "etag": null,
      "title_hash": "e47f2cf7047cfdba8d6e50a8c83d3d49bd967ec099a48462d347833531bf4f84",
      "health_score": 1,
      "volatility": "stable",
      "change_count_12m": 2,
      "last_change_detected": "2026-01-26",
      "citation_risk": "low",
      "recommended_action": "safe_to_cite",
      "signals": []
    },
    {
      "name": "Underfitting",
      "url": "https://en.wikipedia.org/wiki/Underfitting",
      "observed_at": "2026-01-29T03:24:25.966Z",
      "http_status": 200,
      "response_time_ms": 304,
      "content_length": 0,
      "etag": null,
      "title_hash": "e47f2cf7047cfdba8d6e50a8c83d3d49bd967ec099a48462d347833531bf4f84",
      "health_score": 1,
      "volatility": "moderate",
      "change_count_12m": 3,
      "last_change_detected": "2026-01-27",
      "citation_risk": "low",
      "recommended_action": "safe_to_cite",
      "signals": []
    },
    {
      "name": "Bias–variance tradeoff",
      "url": "https://en.wikipedia.org/wiki/Bias%E2%80%93variance_tradeoff",
      "observed_at": "2026-01-29T03:24:25.987Z",
      "http_status": 200,
      "response_time_ms": 21,
      "content_length": 51858,
      "etag": null,
      "title_hash": "e47f2cf7047cfdba8d6e50a8c83d3d49bd967ec099a48462d347833531bf4f84",
      "health_score": 1,
      "volatility": "moderate",
      "change_count_12m": 3,
      "last_change_detected": "2026-01-26",
      "citation_risk": "low",
      "recommended_action": "safe_to_cite",
      "signals": []
    },
    {
      "name": "Explainable artificial intelligence",
      "url": "https://en.wikipedia.org/wiki/Explainable_artificial_intelligence",
      "observed_at": "2026-01-29T03:24:26.046Z",
      "http_status": 200,
      "response_time_ms": 59,
      "content_length": 70442,
      "etag": null,
      "title_hash": "e47f2cf7047cfdba8d6e50a8c83d3d49bd967ec099a48462d347833531bf4f84",
      "health_score": 1,
      "volatility": "moderate",
      "change_count_12m": 3,
      "last_change_detected": "2026-01-28",
      "citation_risk": "low",
      "recommended_action": "safe_to_cite",
      "signals": []
    },
    {
      "name": "AI safety",
      "url": "https://en.wikipedia.org/wiki/AI_safety",
      "observed_at": "2026-01-29T03:24:26.357Z",
      "http_status": 200,
      "response_time_ms": 311,
      "content_length": 0,
      "etag": null,
      "title_hash": "e47f2cf7047cfdba8d6e50a8c83d3d49bd967ec099a48462d347833531bf4f84",
      "health_score": 0.8,
      "volatility": "moderate",
      "change_count_12m": 3,
      "last_change_detected": "2026-01-29",
      "citation_risk": "low",
      "recommended_action": "safe_to_cite",
      "signals": [
        "content_shift"
      ]
    },
    {
      "name": "Algorithmic bias",
      "url": "https://en.wikipedia.org/wiki/Algorithmic_bias",
      "observed_at": "2026-01-29T03:24:26.687Z",
      "http_status": 200,
      "response_time_ms": 330,
      "content_length": 0,
      "etag": null,
      "title_hash": "e47f2cf7047cfdba8d6e50a8c83d3d49bd967ec099a48462d347833531bf4f84",
      "health_score": 0.8,
      "volatility": "moderate",
      "change_count_12m": 4,
      "last_change_detected": "2026-01-29",
      "citation_risk": "low",
      "recommended_action": "safe_to_cite",
      "signals": [
        "content_shift"
      ]
    },
    {
      "name": "Ethics of artificial intelligence",
      "url": "https://en.wikipedia.org/wiki/Ethics_of_artificial_intelligence",
      "observed_at": "2026-01-29T03:24:27.007Z",
      "http_status": 200,
      "response_time_ms": 320,
      "content_length": 0,
      "etag": null,
      "title_hash": "e47f2cf7047cfdba8d6e50a8c83d3d49bd967ec099a48462d347833531bf4f84",
      "health_score": 0.8,
      "volatility": "stable",
      "change_count_12m": 2,
      "last_change_detected": "2026-01-29",
      "citation_risk": "low",
      "recommended_action": "safe_to_cite",
      "signals": [
        "content_shift"
      ]
    },
    {
      "name": "AI governance",
      "url": "https://en.wikipedia.org/wiki/AI_governance",
      "observed_at": "2026-01-29T03:24:27.063Z",
      "http_status": 200,
      "response_time_ms": 56,
      "content_length": 94307,
      "etag": null,
      "title_hash": "e47f2cf7047cfdba8d6e50a8c83d3d49bd967ec099a48462d347833531bf4f84",
      "health_score": 1,
      "volatility": "stable",
      "change_count_12m": 2,
      "last_change_detected": "2026-01-19",
      "citation_risk": "low",
      "recommended_action": "safe_to_cite",
      "signals": []
    },
    {
      "name": "Autonomous weapons",
      "url": "https://en.wikipedia.org/wiki/Autonomous_weapons",
      "observed_at": "2026-01-29T03:24:27.234Z",
      "http_status": 200,
      "response_time_ms": 171,
      "content_length": 0,
      "etag": null,
      "title_hash": "e47f2cf7047cfdba8d6e50a8c83d3d49bd967ec099a48462d347833531bf4f84",
      "health_score": 1,
      "volatility": "moderate",
      "change_count_12m": 3,
      "last_change_detected": "2026-01-25",
      "citation_risk": "low",
      "recommended_action": "safe_to_cite",
      "signals": []
    },
    {
      "name": "Training data",
      "url": "https://en.wikipedia.org/wiki/Training_data",
      "observed_at": "2026-01-29T03:24:27.630Z",
      "http_status": 200,
      "response_time_ms": 396,
      "content_length": 0,
      "etag": null,
      "title_hash": "e47f2cf7047cfdba8d6e50a8c83d3d49bd967ec099a48462d347833531bf4f84",
      "health_score": 0.8,
      "volatility": "moderate",
      "change_count_12m": 4,
      "last_change_detected": "2026-01-29",
      "citation_risk": "low",
      "recommended_action": "safe_to_cite",
      "signals": [
        "content_shift"
      ]
    },
    {
      "name": "Big data",
      "url": "https://en.wikipedia.org/wiki/Big_data",
      "observed_at": "2026-01-29T03:24:27.667Z",
      "http_status": 200,
      "response_time_ms": 37,
      "content_length": 119049,
      "etag": null,
      "title_hash": "e47f2cf7047cfdba8d6e50a8c83d3d49bd967ec099a48462d347833531bf4f84",
      "health_score": 1,
      "volatility": "moderate",
      "change_count_12m": 5,
      "last_change_detected": "2026-01-28",
      "citation_risk": "low",
      "recommended_action": "safe_to_cite",
      "signals": []
    },
    {
      "name": "Data labeling",
      "url": "https://en.wikipedia.org/wiki/Data_labeling",
      "observed_at": "2026-01-29T03:24:27.815Z",
      "http_status": 200,
      "response_time_ms": 148,
      "content_length": 0,
      "etag": null,
      "title_hash": "e47f2cf7047cfdba8d6e50a8c83d3d49bd967ec099a48462d347833531bf4f84",
      "health_score": 1,
      "volatility": "moderate",
      "change_count_12m": 3,
      "last_change_detected": "2026-01-25",
      "citation_risk": "low",
      "recommended_action": "safe_to_cite",
      "signals": []
    },
    {
      "name": "Model training",
      "url": "https://en.wikipedia.org/wiki/Training_(machine_learning)",
      "observed_at": "2026-01-29T03:24:28.120Z",
      "http_status": 404,
      "response_time_ms": 305,
      "content_length": 0,
      "etag": null,
      "title_hash": "e47f2cf7047cfdba8d6e50a8c83d3d49bd967ec099a48462d347833531bf4f84",
      "health_score": 0.4,
      "volatility": "stable",
      "change_count_12m": 0,
      "last_change_detected": null,
      "citation_risk": "medium",
      "recommended_action": "archive_before_citing",
      "signals": [
        "http_error",
        "no_last_modified"
      ]
    },
    {
      "name": "Inference engine",
      "url": "https://en.wikipedia.org/wiki/Inference_engine",
      "observed_at": "2026-01-29T03:24:28.140Z",
      "http_status": 200,
      "response_time_ms": 20,
      "content_length": 23081,
      "etag": null,
      "title_hash": "e47f2cf7047cfdba8d6e50a8c83d3d49bd967ec099a48462d347833531bf4f84",
      "health_score": 1,
      "volatility": "stable",
      "change_count_12m": 2,
      "last_change_detected": "2026-01-23",
      "citation_risk": "low",
      "recommended_action": "safe_to_cite",
      "signals": []
    },
    {
      "name": "Artificial intelligence in healthcare",
      "url": "https://en.wikipedia.org/wiki/Artificial_intelligence_in_healthcare",
      "observed_at": "2026-01-29T03:24:28.159Z",
      "http_status": 200,
      "response_time_ms": 19,
      "content_length": 114943,
      "etag": null,
      "title_hash": "e47f2cf7047cfdba8d6e50a8c83d3d49bd967ec099a48462d347833531bf4f84",
      "health_score": 1,
      "volatility": "stable",
      "change_count_12m": 2,
      "last_change_detected": "2026-01-26",
      "citation_risk": "low",
      "recommended_action": "safe_to_cite",
      "signals": []
    },
    {
      "name": "Artificial intelligence in finance",
      "url": "https://en.wikipedia.org/wiki/Artificial_intelligence_in_finance",
      "observed_at": "2026-01-29T03:24:28.467Z",
      "http_status": 200,
      "response_time_ms": 308,
      "content_length": 0,
      "etag": null,
      "title_hash": "e47f2cf7047cfdba8d6e50a8c83d3d49bd967ec099a48462d347833531bf4f84",
      "health_score": 0.8,
      "volatility": "stable",
      "change_count_12m": 2,
      "last_change_detected": "2026-01-29",
      "citation_risk": "low",
      "recommended_action": "safe_to_cite",
      "signals": [
        "content_shift"
      ]
    },
    {
      "name": "Artificial intelligence in education",
      "url": "https://en.wikipedia.org/wiki/Artificial_intelligence_in_education",
      "observed_at": "2026-01-29T03:24:28.489Z",
      "http_status": 200,
      "response_time_ms": 22,
      "content_length": 29475,
      "etag": null,
      "title_hash": "e47f2cf7047cfdba8d6e50a8c83d3d49bd967ec099a48462d347833531bf4f84",
      "health_score": 1,
      "volatility": "stable",
      "change_count_12m": 2,
      "last_change_detected": "2026-01-23",
      "citation_risk": "low",
      "recommended_action": "safe_to_cite",
      "signals": []
    },
    {
      "name": "Artificial intelligence in warfare",
      "url": "https://en.wikipedia.org/wiki/Artificial_intelligence_in_warfare",
      "observed_at": "2026-01-29T03:24:28.581Z",
      "http_status": 200,
      "response_time_ms": 92,
      "content_length": 26796,
      "etag": null,
      "title_hash": "e47f2cf7047cfdba8d6e50a8c83d3d49bd967ec099a48462d347833531bf4f84",
      "health_score": 1,
      "volatility": "stable",
      "change_count_12m": 2,
      "last_change_detected": "2026-01-25",
      "citation_risk": "low",
      "recommended_action": "safe_to_cite",
      "signals": []
    },
    {
      "name": "Recommender system",
      "url": "https://en.wikipedia.org/wiki/Recommender_system",
      "observed_at": "2026-01-29T03:24:28.603Z",
      "http_status": 200,
      "response_time_ms": 22,
      "content_length": 83579,
      "etag": null,
      "title_hash": "e47f2cf7047cfdba8d6e50a8c83d3d49bd967ec099a48462d347833531bf4f84",
      "health_score": 1,
      "volatility": "stable",
      "change_count_12m": 1,
      "last_change_detected": "2026-01-26",
      "citation_risk": "low",
      "recommended_action": "safe_to_cite",
      "signals": []
    },
    {
      "name": "Generative artificial intelligence",
      "url": "https://en.wikipedia.org/wiki/Generative_artificial_intelligence",
      "observed_at": "2026-01-29T03:24:28.625Z",
      "http_status": 200,
      "response_time_ms": 22,
      "content_length": 114346,
      "etag": null,
      "title_hash": "e47f2cf7047cfdba8d6e50a8c83d3d49bd967ec099a48462d347833531bf4f84",
      "health_score": 1,
      "volatility": "moderate",
      "change_count_12m": 3,
      "last_change_detected": "2026-01-28",
      "citation_risk": "low",
      "recommended_action": "safe_to_cite",
      "signals": []
    },
    {
      "name": "Large language model",
      "url": "https://en.wikipedia.org/wiki/Large_language_model",
      "observed_at": "2026-01-29T03:24:28.645Z",
      "http_status": 200,
      "response_time_ms": 20,
      "content_length": 140743,
      "etag": null,
      "title_hash": "e47f2cf7047cfdba8d6e50a8c83d3d49bd967ec099a48462d347833531bf4f84",
      "health_score": 1,
      "volatility": "stable",
      "change_count_12m": 1,
      "last_change_detected": "2026-01-16",
      "citation_risk": "low",
      "recommended_action": "safe_to_cite",
      "signals": []
    },
    {
      "name": "Chatbot",
      "url": "https://en.wikipedia.org/wiki/Chatbot",
      "observed_at": "2026-01-29T03:24:28.664Z",
      "http_status": 200,
      "response_time_ms": 19,
      "content_length": 72853,
      "etag": null,
      "title_hash": "e47f2cf7047cfdba8d6e50a8c83d3d49bd967ec099a48462d347833531bf4f84",
      "health_score": 1,
      "volatility": "stable",
      "change_count_12m": 0,
      "last_change_detected": null,
      "citation_risk": "low",
      "recommended_action": "safe_to_cite",
      "signals": []
    },
    {
      "name": "Artificial intelligence regulation",
      "url": "https://en.wikipedia.org/wiki/Artificial_intelligence_regulation",
      "observed_at": "2026-01-29T03:24:28.805Z",
      "http_status": 200,
      "response_time_ms": 141,
      "content_length": 94316,
      "etag": null,
      "title_hash": "e47f2cf7047cfdba8d6e50a8c83d3d49bd967ec099a48462d347833531bf4f84",
      "health_score": 1,
      "volatility": "stable",
      "change_count_12m": 0,
      "last_change_detected": null,
      "citation_risk": "low",
      "recommended_action": "safe_to_cite",
      "signals": []
    },
    {
      "name": "Artificial intelligence applications",
      "url": "https://en.wikipedia.org/wiki/Applications_of_artificial_intelligence",
      "observed_at": "2026-01-29T03:24:28.824Z",
      "http_status": 200,
      "response_time_ms": 19,
      "content_length": 156924,
      "etag": null,
      "title_hash": "e47f2cf7047cfdba8d6e50a8c83d3d49bd967ec099a48462d347833531bf4f84",
      "health_score": 1,
      "volatility": "moderate",
      "change_count_12m": 3,
      "last_change_detected": "2026-01-23",
      "citation_risk": "low",
      "recommended_action": "safe_to_cite",
      "signals": []
    }
  ]
}